clink/__init__.py
clink/__main__.py
clink/api.py
clink/clink.py
clink/handlers.py
clink/listeners.py
clink/participants.py
clink/py.typed
clink/settings.py
clink/backends/__init__.py
clink/backends/base.py
clink/backends/dummy.py
clink/backends/kombu.py
clink/messaging/__init__.py
clink/messaging/base.py
clink/messaging/commands.py
clink/messaging/events.py
clink/messaging/trace_context.py
clink/utils/__init__.py
clink/utils/decorators.py
clink/utils/functional.py
clink/utils/participants.py
clink/utils/sentry.py
clink-0.35.0.dist-info/AUTHORS.rst
clink-0.35.0.dist-info/LICENSE
clink-0.35.0.dist-info/LICENSE-cloudevents
clink-0.35.0.dist-info/LICENSE-django
clink-0.35.0.dist-info/LICENSE-kombu
clink-0.35.0.dist-info/LICENSE-w3c
clink-0.35.0.dist-info/METADATA
clink-0.35.0.dist-info/WHEEL
clink-0.35.0.dist-info/entry_points.txt
clink-0.35.0.dist-info/top_level.txt
clink-0.35.0.dist-info/RECORD
